birch/__init__.py
birch/_version.py
birch/casters.py
birch/core.py
birch/exceptions.py
birch/paths.py
tests/__init__.py
tests/test_core.py
tests/test_default_casters.py
birch-0.0.35.dist-info/LICENSE
birch-0.0.35.dist-info/METADATA
birch-0.0.35.dist-info/WHEEL
birch-0.0.35.dist-info/top_level.txt
birch-0.0.35.dist-info/RECORD
